pymafia/__init__.py
pymafia/ash/__init__.py
pymafia/ash/conversion.py
pymafia/ash/function.py
pymafia/ash/library.py
pymafia/combat.py
pymafia/datatypes/__init__.py
pymafia/datatypes/bounty.py
pymafia/datatypes/class_.py
pymafia/datatypes/coinmaster.py
pymafia/datatypes/effect.py
pymafia/datatypes/element.py
pymafia/datatypes/familiar.py
pymafia/datatypes/item.py
pymafia/datatypes/location.py
pymafia/datatypes/modifier.py
pymafia/datatypes/monster.py
pymafia/datatypes/path.py
pymafia/datatypes/phylum.py
pymafia/datatypes/servant.py
pymafia/datatypes/skill.py
pymafia/datatypes/slot.py
pymafia/datatypes/stat.py
pymafia/datatypes/thrall.py
pymafia/datatypes/vykea.py
pymafia/iotms/__init__.py
pymafia/iotms/barrel_god.py
pymafia/iotms/boxing_daycare.py
pymafia/iotms/cartography.py
pymafia/iotms/cosplay_saber.py
pymafia/iotms/crimbo_shrub.py
pymafia/iotms/god_lobster.py
pymafia/iotms/love_tunnel.py
pymafia/iotms/mumming_trunk.py
pymafia/iotms/pantogram.py
pymafia/iotms/protonic_pack.py
pymafia/iotms/snojo.py
pymafia/iotms/songboom.py
pymafia/iotms/stomping_boots.py
pymafia/iotms/witchess.py
pymafia/kolmafia/__init__.py
pymafia/kolmafia/kolmafia.py
pymafia/kolmafia/patch.py
pymafia/player.py
pymafia/preference.py
pymafia/utils.py
pymafia_config.py
pymafia-0.2.4.dist-info/LICENSE
pymafia-0.2.4.dist-info/METADATA
pymafia-0.2.4.dist-info/WHEEL
pymafia-0.2.4.dist-info/RECORD
