Metadata-Version: 2.1
Name: pymafia
Version: 0.2.4
Summary: A Python module and bridge for reflecting KoLmafia's Java environment
Home-page: https://github.com/MrFizzyBubbs/pymafia
License: MIT
Author: MrFizzyBubbs
Author-email: MrFizzyBubbs@protonmail.com
Requires-Python: >=3.10,<4.0
Classifier: License :: OSI Approved :: MIT License
Classifier: Programming Language :: Python :: 3
Classifier: Programming Language :: Python :: 3.10
Classifier: Programming Language :: Python :: 3.11
Requires-Dist: JPype1 (>=1.4.1,<2.0.0)
Requires-Dist: wrapt (>=1.15.0,<2.0.0)
Project-URL: Repository, https://github.com/MrFizzyBubbs/pymafia
